Workbook

Sheet README
A1: Group Month-End Close & Financial Reporting Project
A2: Portfolio project designed to demonstrate financial accounting, reconciliations, reporting, controls and process improvement.
A4: Project objective | B4: Complete a simulated month-end close for a UK group holding company.
A5: Reporting period | B5: 30 September 2026
A6: Currency | B6: GBP
A7: Entity | B7: AVERRA Holdings Ltd (simulated)
A8: Key skills demonstrated | B8: Month-end close, journals, reconciliations, financial statements, variance analysis, controls and audit readiness.
A9: Important note | B9: All company names and financial data in this workbook are simulated for portfolio/interview purposes.
A12: Workflow
A13: 1. Review GL transactions
A14: 2. Post adjusting journals
A15: 3. Prepare adjusted trial balance
A16: 4. Complete balance-sheet reconciliations
A17: 5. Prepare P&L and Balance Sheet
A18: 6. Prepare cash-flow summary
A19: 7. Investigate variances
A20: 8. Complete close checklist and management commentary

Sheet GL_Data
A1: General Ledger Data
A2: September 2026 simulated transaction listing
A3: Date | B3: Entity | C3: Account Code | D3: Account Name | E3: Type | F3: Description | G3: Debit | H3: Credit
A4: 01/09/2026 | B4: AVERRA Holdings Ltd | C4: 1000 | D4: Bank | E4: BS | F4: Opening bank balance | G4: 150000 | H4: 0
A5: 02/09/2026 | B5: AVERRA Holdings Ltd | C5: 4000 | D5: Revenue | E5: P&L | F5: Management service revenue | G5: 0 | H5: 95000
A6: 03/09/2026 | B6: AVERRA Holdings Ltd | C6: 5000 | D6: Cost of Sales | E6: P&L | F6: External contractor costs | G6: 42000 | H6: 0
A7: 04/09/2026 | B7: AVERRA Holdings Ltd | C7: 6100 | D7: Salaries | E7: P&L | F7: September payroll | G7: 18000 | H7: 0
A8: 05/09/2026 | B8: AVERRA Holdings Ltd | C8: 6200 | D8: Employer NI | E8: P&L | F8: Employer payroll costs | G8: 2500 | H8: 0
A9: 06/09/2026 | B9: AVERRA Holdings Ltd | C9: 6300 | D9: Rent & Premises | E9: P&L | F9: Office rent | G9: 3500 | H9: 0
A10: 07/09/2026 | B10: AVERRA Holdings Ltd | C10: 6400 | D10: Software & IT | E10: P&L | F10: Software subscriptions | G10: 2200 | H10: 0
A11: 08/09/2026 | B11: AVERRA Holdings Ltd | C11: 6500 | D11: Professional Fees | E11: P&L | F11: Legal/accounting fees | G11: 3000 | H11: 0
A12: 09/09/2026 | B12: AVERRA Holdings Ltd | C12: 1100 | D12: Trade Receivables | E12: BS | F12: Customer invoices | G12: 95000 | H12: 0
A13: 10/09/2026 | B13: AVERRA Holdings Ltd | C13: 1000 | D13: Bank | E13: BS | F13: Customer receipt | G13: 70000 | H13: 0
A14: 10/09/2026 | B14: AVERRA Holdings Ltd | C14: 1100 | D14: Trade Receivables | E14: BS | F14: Customer receipt | G14: 0 | H14: 70000
A15: 12/09/2026 | B15: AVERRA Holdings Ltd | C15: 2000 | D15: Trade Payables | E15: BS | F15: Supplier invoices | G15: 0 | H15: 42000
... A28: 29/09/2026 | B28: AVERRA Holdings Ltd | C28: 1000 | D28: Bank | E28: BS | F28: FX/other income | G28: 1200 | H28: 0

Sheet Adjusting_Journals
A1: Adjusting Journals
A2: Month-end entries for accruals, depreciation and prepayments
A3: JE No. | B3: Date | C3: Account Code | D3: Account Name | E3: Description | F3: Debit | G3: Credit | H3: Reason
A4: AJ001 | B4: 30/09/2026 | C4: 6400 | D4: Software & IT | E4: Accrue September software invoice not yet received | F4: 800 | G4: 0 | H4: Accrual
A5: AJ001 | B5: 30/09/2026 | C5: 2100 | D5: Accrued Expenses | E5: Accrue September software invoice not yet received | F5: 0 | G5: 800 | H5: Accrual
A6: AJ002 | B6: 30/09/2026 | C6: 6300 | D6: Rent & Premises | E6: Accrue utilities/rent-related cost | F6: 1200 | G6: 0 | H6: Accrual
A7: AJ002 | B7: 30/09/2026 | C7: 2100 | D7: Accrued Expenses | E7: Accrue utilities/rent-related cost | F7: 0 | G7: 1200 | H7: Accrual
A8: AJ003 | B8: 30/09/2026 | C8: 6800 | D8: Depreciation | E8: Monthly depreciation on equipment | F8: 200 | G8: 0 | H8: Depreciation
A9: AJ003 | B9: 30/09/2026 | C9: 1550 | D9: Accumulated Depreciation | E9: Monthly depreciation on equipment | F9: 0 | G9: 200 | H9: Depreciation
A10: AJ004 | B10: 30/09/2026 | C10: 6300 | D10: Rent & Premises | E10: Insurance/prepayment release for one month | F10: 1000 | G10: 0 | H10: Prepayment release
A11: AJ004 | B11: 30/09/2026 | C11: 1200 | D11: Prepayments | E11: Insurance/prepayment release for one month | F11: 0 | G11: 1000 | H11: Prepayment release
A12: AJ005 | B12: 30/09/2026 | C12: 5000 | D12: Cost of Sales | E12: Unbilled contractor cost accrued | F12: 3500 | G12: 0 | H12: Accrual
A13: AJ005 | B13: 30/09/2026 | C13: 2100 | D13: Accrued Expenses | E13: Unbilled contractor cost accrued | F13: 0 | G13: 3500 | H13: Accrual

Sheet Trial_Balance
A1: Adjusted Trial Balance
A2: Formula-driven from GL data and month-end journals
A3: Account Code | B3: Account Name | C3: Category | D3: Debit | E3: Credit | F3: Balance
A4: 1000 | B4: Bank | C4: Balance Sheet | D4: =SUMIF(GL_Data!$C:$C,A4,GL_Data!$G:$G)+SUMIF(Adjusting_Journals!$C:$C,A4,Adjusting_Journals!$F:$F) -> 271200 | E4: =SUMIF(GL_Data!$C:$C,A4,GL_Data!$H:$H)+SUMIF(Adjusting_Journals!$C:$C,A4,Adjusting_Journals!$G:$G) -> 47450 | F4: =D4-E4 -> 223750
A5: 1100 | B5: Trade Receivables | C5: Balance Sheet | D5: =SUMIF(GL_Data!$C:$C,A5,GL_Data!$G:$G)+SUMIF(Adjusting_Journals!$C:$C,A5,Adjusting_Journals!$F:$F) -> 95000 | E5: =SUMIF(GL_Data!$C:$C,A5,GL_Data!$H:$H)+SUMIF(Adjusting_Journals!$C:$C,A5,Adjusting_Journals!$G:$G) -> 70000 | F5: =D5-E5 -> 25000
A6: 1200 | B6: Prepayments | C6: Balance Sheet | D6: =SUMIF(GL_Data!$C:$C,A6,GL_Data!$G:$G)+SUMIF(Adjusting_Journals!$C:$C,A6,Adjusting_Journals!$F:$F) -> 12000 | E6: =SUMIF(GL_Data!$C:$C,A6,GL_Data!$H:$H)+SUMIF(Adjusting_Journals!$C:$C,A6,Adjusting_Journals!$G:$G) -> 1000 | F6: =D6-E6 -> 11000
A7: 1500 | B7: Fixed Assets | C7: Balance Sheet | D7: =SUMIF(GL_Data!$C:$C,A7,GL_Data!$G:$G)+SUMIF(Adjusting_Journals!$C:$C,A7,Adjusting_Journals!$F:$F) -> 10000 | E7: =SUMIF(GL_Data!$C:$C,A7,GL_Data!$H:$H)+SUMIF(Adjusting_Journals!$C:$C,A7,Adjusting_Journals!$G:$G) -> 0 | F7: =D7-E7 -> 10000
A8: 1550 | B8: Accumulated Depreciation | C8: Balance Sheet | D8: =SUMIF(GL_Data!$C:$C,A8,GL_Data!$G:$G)+SUMIF(Adjusting_Journals!$C:$C,A8,Adjusting_Journals!$F:$F) -> 0 | E8: =SUMIF(GL_Data!$C:$C,A8,GL_Data!$H:$H)+SUMIF(Adjusting_Journals!$C:$C,A8,Adjusting_Journals!$G:$G) -> 200 | F8: =D8-E8 -> -200
A9: 2000 | B9: Trade Payables | C9: Balance Sheet | D9: =SUMIF(GL_Data!$C:$C,A9,GL_Data!$G:$G)+SUMIF(Adjusting_Journals!$C:$C,A9,Adjusting_Journals!$F:$F) -> 25000 | E9: =SUMIF(GL_Data!$C:$C,A9,GL_Data!$H:$H)+SUMIF(Adjusting_Journals!$C:$C,A9,Adjusting_Journals!$G:$G) -> 42000 | F9: =D9-E9 -> -17000
A10: 2100 | B10: Accrued Expenses | C10: Balance Sheet | D10: =SUMIF(GL_Data!$C:$C,A10,GL_Data!$G:$G)+SUMIF(Adjusting_Journals!$C:$C,A10,Adjusting_Journals!$F:$F) -> 0 | E10: =SUMIF(GL_Data!$C:$C,A10,GL_Data!$H:$H)+SUMIF(Adjusting_Journals!$C:$C,A10,Adjusting_Journals!$G:$G) -> 5500 | F10: =D10-E10 -> -5500
A11: 3000 | B11: Share Capital | C11: Balance Sheet | D11: =SUMIF(GL_Data!$C:$C,A11,GL_Data!$G:$G)+SUMIF(Adjusting_Journals!$C:$C,A11,Adjusting_Journals!$F:$F) -> 0 | E11: =SUMIF(GL_Data!$C:$C,A11,GL_Data!$H:$H)+SUMIF(Adjusting_Journals!$C:$C,A11,Adjusting_Journals!$G:$G) -> 50000 | F11: =D11-E11 -> -50000
A12: 4000 | B12: Revenue | C12: Profit & Loss | D12: =SUMIF(GL_Data!$C:$C,A12,GL_Data!$G:$G)+SUMIF(Adjusting_Journals!$C:$C,A12,Adjusting_Journals!$F:$F) -> 0 | E12: =SUMIF(GL_Data!$C:$C,A12,GL_Data!$H:$H)+SUMIF(Adjusting_Journals!$C:$C,A12,Adjusting_Journals!$G:$G) -> 95000 | F12: =D12-E12 -> -95000
A13: 5000 | B13: Cost of Sales | C13: Profit & Loss | D13: =SUMIF(GL_Data!$C:$C,A13,GL_Data!$G:$G)+SUMIF(Adjusting_Journals!$C:$C,A13,Adjusting_Journals!$F:$F) -> 45500 | E13: =SUMIF(GL_Data!$C:$C,A13,GL_Data!$H:$H)+SUMIF(Adjusting_Journals!$C:$C,A13,Adjusting_Journals!$G:$G) -> 0 | F13: =D13-E13 -> 45500
A14: 6100 | B14: Salaries | C14: Profit & Loss | D14: =SUMIF(GL_Data!$C:$C,A14,GL_Data!$G:$G)+SUMIF(Adjusting_Journals!$C:$C,A14,Adjusting_Journals!$F:$F) -> 18000 | E14: =SUMIF(GL_Data!$C:$C,A14,GL_Data!$H:$H)+SUMIF(Adjusting_Journals!$C:$C,A14,Adjusting_Journals!$G:$G) -> 0 | F14: =D14-E14 -> 18000
A15: 6200 | B15: Employer NI | C15: Profit & Loss | D15: =SUMIF(GL_Data!$C:$C,A15,GL_Data!$G:$G)+SUMIF(Adjusting_Journals!$C:$C,A15,Adjusting_Journals!$F:$F) -> 2500 | E15: =SUMIF(GL_Data!$C:$C,A15,GL_Data!$H:$H)+SUMIF(Adjusting_Journals!$C:$C,A15,Adjusting_Journals!$G:$G) -> 0 | F15: =D15-E15 -> 2500
... A21: 7000 | B21: Other Income | C21: Profit & Loss | D21: =SUMIF(GL_Data!$C:$C,A21,GL_Data!$G:$G)+SUMIF(Adjusting_Journals!$C:$C,A21,Adjusting_Journals!$F:$F) -> 0 | E21: =SUMIF(GL_Data!$C:$C,A21,GL_Data!$H:$H)+SUMIF(Adjusting_Journals!$C:$C,A21,Adjusting_Journals!$G:$G) -> 1200 | F21: =D21-E21 -> -1200
A23: TOTAL | D23: =SUM(D4:D21) -> 493350 | E23: =SUM(E4:E21) -> 312350 | F23: =SUM(F4:F21) -> 181000

Sheet BS_Recon
A1: Balance Sheet Reconciliation
A2: Identify differences between ledger balances and independent supporting schedules
A3: Account | B3: GL Balance | C3: Supporting Balance | D3: Difference | E3: Status | F3: Investigation / Action
A4: Bank | B4: =SUMIF(Trial_Balance!$B:$B,A4,Trial_Balance!$F:$F) -> 223750 | C4: 183950 | D4: =B4-C4 -> 39800 | E4: =IF(ABS(D4)<0.01,"RECONCILED","INVESTIGATE") -> INVESTIGATE | F4: Agree to bank statement; investigate timing items
A5: Trade Receivables | B5: =SUMIF(Trial_Balance!$B:$B,A5,Trial_Balance!$F:$F) -> 25000 | C5: 25000 | D5: =B5-C5 -> 0 | E5: =IF(ABS(D5)<0.01,"RECONCILED","INVESTIGATE") -> RECONCILED | F5: Agree aged receivables to customer ledger
A6: Prepayments | B6: =SUMIF(Trial_Balance!$B:$B,A6,Trial_Balance!$F:$F) -> 11000 | C6: 11000 | D6: =B6-C6 -> 0 | E6: =IF(ABS(D6)<0.01,"RECONCILED","INVESTIGATE") -> RECONCILED | F6: Recalculate remaining insurance prepayment
A7: Fixed Assets | B7: =SUMIF(Trial_Balance!$B:$B,A7,Trial_Balance!$F:$F) -> 10000 | C7: 10000 | D7: =B7-C7 -> 0 | E7: =IF(ABS(D7)<0.01,"RECONCILED","INVESTIGATE") -> RECONCILED | F7: Agree additions to invoice/fixed asset register
A8: Accumulated Depreciation | B8: =SUMIF(Trial_Balance!$B:$B,A8,Trial_Balance!$F:$F) -> -200 | C8: -200 | D8: =B8-C8 -> 0 | E8: =IF(ABS(D8)<0.01,"RECONCILED","INVESTIGATE") -> RECONCILED | F8: Agree monthly depreciation calculation
A9: Trade Payables | B9: =SUMIF(Trial_Balance!$B:$B,A9,Trial_Balance!$F:$F) -> -17000 | C9: 17000 | D9: =B9-C9 -> -34000 | E9: =IF(ABS(D9)<0.01,"RECONCILED","INVESTIGATE") -> INVESTIGATE | F9: Agree supplier ledger and unpaid invoices
A10: Accrued Expenses | B10: =SUMIF(Trial_Balance!$B:$B,A10,Trial_Balance!$F:$F) -> -5500 | C10: 6700 | D10: =B10-C10 -> -12200 | E10: =IF(ABS(D10)<0.01,"RECONCILED","INVESTIGATE") -> INVESTIGATE | F10: Agree accrual support and reverse when invoiced

Sheet P&L
A1: Statement of Profit or Loss
A2: September 2026
A3: Line Item | B3: Amount
A4: Revenue | B4: =SUMIF(Trial_Balance!$A:$A,"4000",Trial_Balance!$F:$F)*1 -> -95000
A5: Other Income | B5: =SUMIF(Trial_Balance!$A:$A,"7000",Trial_Balance!$F:$F)*1 -> -1200
A6: Cost of Sales | B6: =SUMIF(Trial_Balance!$A:$A,"5000",Trial_Balance!$F:$F)*-1 -> -45500
A7: Salaries | B7: =SUMIF(Trial_Balance!$A:$A,"6100",Trial_Balance!$F:$F)*-1 -> -18000
A8: Employer NI | B8: =SUMIF(Trial_Balance!$A:$A,"6200",Trial_Balance!$F:$F)*-1 -> -2500
A9: Rent & Premises | B9: =SUMIF(Trial_Balance!$A:$A,"6300",Trial_Balance!$F:$F)*-1 -> -5700
A10: Software & IT | B10: =SUMIF(Trial_Balance!$A:$A,"6400",Trial_Balance!$F:$F)*-1 -> -3000
A11: Professional Fees | B11: =SUMIF(Trial_Balance!$A:$A,"6500",Trial_Balance!$F:$F)*-1 -> -3000
A12: Travel & Expenses | B12: =SUMIF(Trial_Balance!$A:$A,"6700",Trial_Balance!$F:$F)*-1 -> -1800
A13: Bank Charges | B13: =SUMIF(Trial_Balance!$A:$A,"6800",Trial_Balance!$F:$F)*-1 -> -650
A14: Operating / Net Profit | B14: =SUM(B4:B13) -> -176350

Sheet Balance_Sheet
A1: Statement of Financial Position
A2: As at 30 September 2026
A3: Assets | B3: Amount
A4: Bank | B4: =SUMIF(Trial_Balance!$A:$A,"1000",Trial_Balance!$F:$F) -> 223750
A5: Trade Receivables | B5: =SUMIF(Trial_Balance!$A:$A,"1100",Trial_Balance!$F:$F) -> 25000
A6: Prepayments | B6: =SUMIF(Trial_Balance!$A:$A,"1200",Trial_Balance!$F:$F) -> 11000
A7: Fixed Assets | B7: =SUMIF(Trial_Balance!$A:$A,"1500",Trial_Balance!$F:$F) -> 10000
A8: Less: Accumulated Depreciation | B8: =SUMIF(Trial_Balance!$A:$A,"1550",Trial_Balance!$F:$F) -> -200
A10: Total Assets | B10: =SUM(B4:B8) -> 269550
A12: Liabilities & Equity | B12: Amount
A13: Trade Payables | B13: =SUMIF(Trial_Balance!$A:$A,"2000",Trial_Balance!$F:$F)*-1 -> 17000
A14: Accrued Expenses | B14: =SUMIF(Trial_Balance!$A:$A,"2100",Trial_Balance!$F:$F)*-1 -> 5500
A15: Share Capital | B15: =SUMIF(Trial_Balance!$A:$A,"3000",Trial_Balance!$F:$F)*-1 -> 50000
A16: Retained Earnings / Current Profit | B16: ='P&L'!B14 -> -176350
A18: Total Liabilities & Equity | B18: =SUM(B13:B16) -> -103850
A20: Balance Check | B20: =B10-B18 -> 373400

Sheet Cash_Flow
A1: Cash Flow Summary
A2: September 2026 indirect-style management summary
A3: Cash Flow Item | B3: Amount
A4: Opening Cash | B4: 150000
A5: Net Profit | B5: ='P&L'!B14 -> -176350
A6: Increase in Trade Receivables | B6: =-(25000-0) -> -25000
A7: Increase in Prepayments | B7: =-(11000-0) -> -11000
A8: Increase in Trade Payables | B8: =17000 -> 17000
A9: Increase in Accrued Expenses | B9: =6700 -> 6700
A10: Capital Expenditure | B10: =-10000 -> -10000
A11: Share Capital Funding | B11: =50000 -> 50000
A12: Closing Cash | B12: =SUM(B4:B11) -> 1350

Sheet Variance_Analysis
A1: P&L Variance Analysis
A2: Actual vs budget – management review
A3: Line Item | B3: Actual | C3: Budget | D3: Variance | E3: Variance % | F3: Comment
A4: Revenue | B4: ='P&L'!B4 -> -95000 | C4: 100000 | D4: =B4-C4 -> -195000 | E4: =IF(C4=0,0,D4/C4) -> -1.95 | F4: Review material variance; document root cause and corrective action.
A5: Other Income | B5: ='P&L'!B5 -> -1200 | C5: 1000 | D5: =B5-C5 -> -2200 | E5: =IF(C5=0,0,D5/C5) -> -2.2 | F5: Review material variance; document root cause and corrective action.
A6: Cost of Sales | B6: ='P&L'!B6 -> -45500 | C6: 40000 | D6: =B6-C6 -> -85500 | E6: =IF(C6=0,0,D6/C6) -> -2.1375 | F6: Review material variance; document root cause and corrective action.
A7: Salaries | B7: ='P&L'!B7 -> -18000 | C7: 17000 | D7: =B7-C7 -> -35000 | E7: =IF(C7=0,0,D7/C7) -> -2.0588235 | F7: Review material variance; document root cause and corrective action.
A8: Employer NI | B8: ='P&L'!B8 -> -2500 | C8: 2400 | D8: =B8-C8 -> -4900 | E8: =IF(C8=0,0,D8/C8) -> -2.0416667 | F8: Review material variance; document root cause and corrective action.
A9: Rent & Premises | B9: ='P&L'!B9 -> -5700 | C9: 3500 | D9: =B9-C9 -> -9200 | E9: =IF(C9=0,0,D9/C9) -> -2.6285714 | F9: Review material variance; document root cause and corrective action.
A10: Software & IT | B10: ='P&L'!B10 -> -3000 | C10: 1800 | D10: =B10-C10 -> -4800 | E10: =IF(C10=0,0,D10/C10) -> -2.6666667 | F10: Review material variance; document root cause and corrective action.
A11: Professional Fees | B11: ='P&L'!B11 -> -3000 | C11: 2500 | D11: =B11-C11 -> -5500 | E11: =IF(C11=0,0,D11/C11) -> -2.2 | F11: Review material variance; document root cause and corrective action.
A12: Travel & Expenses | B12: ='P&L'!B12 -> -1800 | C12: 1500 | D12: =B12-C12 -> -3300 | E12: =IF(C12=0,0,D12/C12) -> -2.2 | F12: Review material variance; document root cause and corrective action.
A13: Bank Charges | B13: ='P&L'!B13 -> -650 | C13: 400 | D13: =B13-C13 -> -1050 | E13: =IF(C13=0,0,D13/C13) -> -2.625 | F13: Review material variance; document root cause and corrective action.

Sheet Close_Checklist
A1: Month-End Close Checklist
A2: Control-focused close tracker
A3: Task | B3: Owner | C3: Due | D3: Status | E3: Evidence / Comment
A4: Obtain final GL and confirm completeness | B4: GL Accountant | C4: 01/10/2026 | D4: Complete | E4: GL imported and reviewed
A5: Post accruals and prepayments | B5: Financial Accountant | C5: 01/10/2026 | D5: Complete | E5: AJ001–AJ005 posted
A6: Reconcile bank | B6: Financial Accountant | C6: 02/10/2026 | D6: Complete | E6: Bank balance agreed
A7: Reconcile AR | B7: GL Accountant | C7: 02/10/2026 | D7: Complete | E7: Customer ledger agreed
A8: Reconcile AP | B8: GL Accountant | C8: 02/10/2026 | D8: Complete | E8: Supplier ledger agreed
A9: Review fixed assets and depreciation | B9: Financial Accountant | C9: 02/10/2026 | D9: Complete | E9: Depreciation journal posted
A10: Review balance sheet reconciliations | B10: Finance Manager | C10: 03/10/2026 | D10: In Review | E10: Review outstanding differences
A11: Prepare management P&L | B11: Financial Accountant | C11: 03/10/2026 | D11: Complete | E11: P&L and variance analysis
A12: Prepare balance sheet | B12: Financial Accountant | C12: 03/10/2026 | D12: Complete | E12: Balance check performed
A13: Management review and sign-off | B13: Finance Manager | C13: 05/10/2026 | D13: Pending | E13: Final sign-off required

Sheet Management_Summary
A1: Management Summary
A2: Executive review of September 2026 financial performance
A4: Revenue | B4: ='P&L'!B4 -> -95000
A5: Other Income | B5: ='P&L'!B5 -> -1200
A6: Total Operating Costs | B6: =-SUM('P&L'!B6:B13) -> 80150
A7: Net Profit | B7: ='P&L'!B14 -> -176350
A8: Closing Cash | B8: =Cash_Flow!B12 -> 1350
A9: Balance Sheet Check | B9: =Balance_Sheet!B20 -> 373400
A12: Key management observations
A13: • Revenue is below the £100k budget and should be investigated with the commercial team.
A14: • Software and professional fees are above budget and should be reviewed for recurring or one-off costs.
A15: • Closing cash is supported by customer receipts and new share capital funding.
A16: • All material balance-sheet accounts should have evidence attached to the reconciliation.
A17: • Month-end close should be supported by documented review and sign-off controls.
